jinjanator_plugin_ansible/__init__.py
jinjanator_plugin_ansible/plugin.py
jinjanator_plugin_ansible/py.typed
jinjanator_plugin_ansible-25.1.0.dist-info/METADATA
jinjanator_plugin_ansible-25.1.0.dist-info/WHEEL
jinjanator_plugin_ansible-25.1.0.dist-info/entry_points.txt
jinjanator_plugin_ansible-25.1.0.dist-info/licenses/LICENSE
jinjanator_plugin_ansible-25.1.0.dist-info/RECORD
