Metadata-Version: 2.4
Name: jinjanator-plugin-ansible
Version: 25.1.0
Summary: Plugin which provides Ansible filters and tests to the jinjanator tool
Project-URL: Bug Tracker, https://github.com/kpfleming/jinjanator-plugin-ansible/issues
Project-URL: Homepage, https://github.com/kpfleming/jinjanator-plugin-ansible
Author-email: "Kevin P. Fleming" <jinjanator@kevin.km6g.us>
License: Apache-2.0
License-File: LICENSE
Classifier: Development Status :: 5 - Production/Stable
Classifier: Environment :: Console
Classifier: Intended Audience :: Developers
Classifier: Intended Audience :: System Administrators
Classifier: Natural Language :: English
Classifier: Operating System :: OS Independent
Classifier: Programming Language :: Python :: 3 :: Only
Classifier: Programming Language :: Python :: 3.10
Classifier: Programming Language :: Python :: 3.11
Classifier: Programming Language :: Python :: 3.12
Classifier: Programming Language :: Python :: 3.13
Classifier: Programming Language :: Python :: 3.14
Classifier: Typing :: Typed
Requires-Python: >=3.10
Requires-Dist: ansible-core
Requires-Dist: jinjanator-plugins==25.1.*
